setup.py
msmexplorer/__init__.py
msmexplorer/utils.py
msmexplorer/version.py
msmexplorer.egg-info/PKG-INFO
msmexplorer.egg-info/SOURCES.txt
msmexplorer.egg-info/dependency_links.txt
msmexplorer.egg-info/not-zip-safe
msmexplorer.egg-info/top_level.txt
msmexplorer/palettes/__init__.py
msmexplorer/palettes/custom.py
msmexplorer/plots/__init__.py
msmexplorer/plots/chord.py
msmexplorer/plots/cluster.py
msmexplorer/plots/msm.py
msmexplorer/plots/projection.py
msmexplorer/plots/timeseries.py
msmexplorer/plots/tpt.py
msmexplorer/tests/__init__.py
msmexplorer/tests/test_chord_plot.py
msmexplorer/tests/test_cluster_plot.py
msmexplorer/tests/test_msm_plot.py
msmexplorer/tests/test_projection_plot.py
msmexplorer/tests/test_timeseries_plot.py
msmexplorer/tests/test_tpt_plot.py
msmexplorer/tests/test_utils.py