Metadata-Version: 1.1
Name: msmexplorer
Version: 1.0.0
Summary: b'|Build Status| |Build status| |Coverage Status| |PyPI version| |License|\n|Documentation| |DOI|'
Home-page: https://github.com/cxhernandez/msmexplorer
Author: Carlos Xavier Hernández
Author-email: cxh@stanford.edu
License: LGPLv2+
Download-URL: https://github.com/cxhernandez/msmexplorer/tarball/master
Keywords: visualizations,biomolecular,simulations,markov state models
Platform: Windows
Platform: Linux
Platform: Mac OS-X
Platform: Unix
Classifier: Intended Audience :: Science/Research
Classifier: License :: OSI Approved :: MIT License
Classifier: Programming Language :: Python
Classifier: Programming Language :: Python :: 3
Classifier: Programming Language :: Python :: 3.4
Classifier: Programming Language :: Python :: 3.5
Classifier: Operating System :: Unix
Classifier: Operating System :: MacOS
Classifier: Operating System :: Microsoft :: Windows
Classifier: Topic :: Scientific/Engineering
